gamest_plugins/diablo_iii/__init__.py
gamest_plugins/diablo_iii/module.py
gamest_plugins_diablo_iii-2.0.4.dist-info/COPYING
gamest_plugins_diablo_iii-2.0.4.dist-info/METADATA
gamest_plugins_diablo_iii-2.0.4.dist-info/WHEEL
gamest_plugins_diablo_iii-2.0.4.dist-info/top_level.txt
gamest_plugins_diablo_iii-2.0.4.dist-info/RECORD
