Metadata-Version: 2.1
Name: gamest-plugins-diablo-iii
Version: 2.0.4
Summary: Report on Diablo III games.
Home-page: https://github.com/sopoforic/gamest_plugins_diablo_iii
Author: Tracy Poff
Author-email: tracy.poff@gmail.com
License: UNKNOWN
Platform: UNKNOWN
Classifier: Development Status :: 4 - Beta
Classifier: Environment :: Plugins
Classifier: Topic :: Games/Entertainment
Requires-Dist: bs4
Requires-Dist: gamest (<4.0,>=2.0)
Requires-Dist: requests
